fast_intensity.cpython-36m-x86_64-linux-gnu.so
fast_intensity-0.4.dist-info/RECORD
fast_intensity-0.4.dist-info/WHEEL
fast_intensity-0.4.dist-info/top_level.txt
fast_intensity-0.4.dist-info/METADATA
