Metadata-Version: 2.1
Name: fast-intensity
Version: 0.4
Summary: Fast intensity inference
Home-page: https://github.com/ComputationalMedicineLab/fast_intensity
Author: Thomas A. Lasko, Jacek Bajor, John M Still
Maintainer: John M Still
Maintainer-email: john.m.still@vumc.org
License: BSD
Platform: UNKNOWN
Classifier: Development Status :: 3 - Alpha
Classifier: Intended Audience :: Developers
Classifier: License :: OSI Approved :: BSD License
Classifier: Programming Language :: Python :: 3
Classifier: Topic :: Scientific/Engineering :: Information Analysis
